spacelang/__init__.py
spacelang/step/__init__.py
spacelang/step/navigate.py
spacelang/step/ship_command.py
spacelang-0.0.0.dist-info/METADATA
spacelang-0.0.0.dist-info/WHEEL
spacelang-0.0.0.dist-info/top_level.txt
spacelang-0.0.0.dist-info/RECORD
