Metadata-Version: 2.1
Name: spacelang
Version: 0.0.0
Summary: A spacetraders automation language
Author-email: Ashwin Naren <arihant2math@gmail.com>
Project-URL: Homepage, https://arihant2math.github.io/spacelang/
Project-URL: Documentation, https://arihant2math.github.io/spacelang/
Project-URL: Bug Tracker, https://github.com/arihant2math/spacelang/issues
Classifier: Programming Language :: Python :: 3
Classifier: License :: OSI Approved :: MIT License
Classifier: Operating System :: OS Independent
Requires-Python: >=3.7
Requires-Dist: autotraders (>=1.1)
Requires-Dist: pyyaml (>=6.0)
